README.md
setup.py
pytorch_train.egg-info/PKG-INFO
pytorch_train.egg-info/SOURCES.txt
pytorch_train.egg-info/dependency_links.txt
pytorch_train.egg-info/top_level.txt
torch_tools/__init__.py
torch_tools/torch_tools.py
torch_tools/torch_tools.pyi